password_checker/__init__.py
password_checker/pc4.py
password_checker-1.0.2.dist-info/LICENSE
password_checker-1.0.2.dist-info/METADATA
password_checker-1.0.2.dist-info/WHEEL
password_checker-1.0.2.dist-info/top_level.txt
password_checker-1.0.2.dist-info/RECORD
